python_iso20022/__init__.py
python_iso20022/acmt/__init__.py
python_iso20022/acmt/acmt_001_001_08/__init__.py
python_iso20022/acmt/acmt_001_001_08/enums.py
python_iso20022/acmt/acmt_001_001_08/models.py
python_iso20022/acmt/acmt_002_001_08/__init__.py
python_iso20022/acmt/acmt_002_001_08/enums.py
python_iso20022/acmt/acmt_002_001_08/models.py
python_iso20022/acmt/acmt_003_001_08/__init__.py
python_iso20022/acmt/acmt_003_001_08/enums.py
python_iso20022/acmt/acmt_003_001_08/models.py
python_iso20022/acmt/acmt_005_001_06/__init__.py
python_iso20022/acmt/acmt_005_001_06/enums.py
python_iso20022/acmt/acmt_005_001_06/models.py
python_iso20022/acmt/acmt_006_001_07/__init__.py
python_iso20022/acmt/acmt_006_001_07/enums.py
python_iso20022/acmt/acmt_006_001_07/models.py
python_iso20022/acmt/acmt_007_001_05/__init__.py
python_iso20022/acmt/acmt_007_001_05/models.py
python_iso20022/acmt/acmt_008_001_05/__init__.py
python_iso20022/acmt/acmt_008_001_05/models.py
python_iso20022/acmt/acmt_009_001_04/__init__.py
python_iso20022/acmt/acmt_009_001_04/models.py
python_iso20022/acmt/acmt_010_001_04/__init__.py
python_iso20022/acmt/acmt_010_001_04/models.py
python_iso20022/acmt/acmt_011_001_04/__init__.py
python_iso20022/acmt/acmt_011_001_04/models.py
python_iso20022/acmt/acmt_012_001_04/__init__.py
python_iso20022/acmt/acmt_012_001_04/models.py
python_iso20022/acmt/acmt_013_001_04/__init__.py
python_iso20022/acmt/acmt_013_001_04/models.py
python_iso20022/acmt/acmt_014_001_05/__init__.py
python_iso20022/acmt/acmt_014_001_05/models.py
python_iso20022/acmt/acmt_015_001_04/__init__.py
python_iso20022/acmt/acmt_015_001_04/models.py
python_iso20022/acmt/acmt_016_001_04/__init__.py
python_iso20022/acmt/acmt_016_001_04/models.py
python_iso20022/acmt/acmt_017_001_04/__init__.py
python_iso20022/acmt/acmt_017_001_04/models.py
python_iso20022/acmt/acmt_018_001_04/__init__.py
python_iso20022/acmt/acmt_018_001_04/models.py
python_iso20022/acmt/acmt_019_001_04/__init__.py
python_iso20022-0.3.0.dist-info/LICENSE
python_iso20022-0.3.0.dist-info/METADATA
python_iso20022-0.3.0.dist-info/WHEEL
python_iso20022-0.3.0.dist-info/RECORD
