Metadata-Version: 2.3
Name: python-iso20022
Version: 0.3.0
Summary: A Python package that automatically generates and updates dataclasses from ISO20022 schemas daily, making it easy to integrate and validate financial message data
License: MIT
Keywords: iso20022,parsing,financial,message
Author: galactixx
Requires-Python: >=3.9
Classifier: License :: OSI Approved :: MIT License
Classifier: Programming Language :: Python :: 3
Classifier: Programming Language :: Python :: 3.9
Classifier: Programming Language :: Python :: 3.10
Classifier: Programming Language :: Python :: 3.11
Classifier: Programming Language :: Python :: 3.12
Classifier: Programming Language :: Python :: 3.13
Requires-Dist: requests (>=2.22.0)
Requires-Dist: xmltodict (>=0.14.1)
Requires-Dist: xsdata (>=21.11)
Project-URL: Homepage, https://github.com/galactixx/python-iso20022
Project-URL: Repository, https://github.com/galactixx/python-iso20022
